{
    "name": "QA 14 - 2023",
    "sections": {
        "QA": [
            "20001",
            "20002",
            "20003",
            "20004",
            "20005",
            "20006",
            "20007",
            "20008",
            "20009",
            "20010",
            "20011",
            "20012",
            "20013",
            "20014",
            "20015",
            "20016",
            "20017",
            "20018",
            "20019",
            "20020",
            "20021",
            "20022"
        ]
    },
    "questions": {
        "20001": {
            "id": "20001",
            "marks": 3,
            "negative_marks": 1.0,
            "is_input_type": true,
            "is_multi_select": false,
            "instructions": "",
            "question_text": "\u00a0\u00a0Q.1 [11916616] \n\t\t\t\t\t\t\t\t\t\t\t\tABC is a triangle having area of 350 cm2. D is a\n\t\t\t\t\t\t\t\t\t\t\t\tpoint on side BC, such that AD is the angle bisector of \u2220CAB. If AB : AC\n\t\t\t\t\t\t\t\t\t\t\t\t= 3 : 4, then what is the area (in cm2) of triangle ADC?",
            "options": [],
            "correct_response": [
                [
                    "1"
                ]
            ],
            "solution": "<b><br><b></b><div><img src=\"https://clsite-file.s3.amazonaws.com/LSTQuestionImg/773334/887087/77s.gif\">"
        },
        "20002": {
            "id": "20002",
            "marks": 3,
            "negative_marks": 1.0,
            "is_input_type": false,
            "is_multi_select": false,
            "instructions": "",
            "question_text": "\u00a0\u00a0Q.2 [11916616] \n\t\t\t\t\t\t\t\t\t\t\tPipes P and Q are inlet pipes while R is an outlet pipe. Pipe P\n\t\t\t\t\t\t\t\t\t\t\tsupplies water at the rate of 30 liters\n\t\t\t\t\t\t\t\t\t\t\tper hour, pipe Q fills the tank in 6 hours while R empties it in 24 hours.\n\t\t\t\t\t\t\t\t\t\t\tThe empty tank gets filled\n\t\t\t\t\t\t\t\t\t\t\tin 2 hours when all the three pipes are opened. Find the capacity of the\n\t\t\t\t\t\t\t\t\t\t\ttank.",
            "options": [
                "40 liters",
                "60 liters",
                "80 liters",
                "90 liters"
            ],
            "correct_response": [
                [
                    "1"
                ]
            ],
            "solution": "<b><br><b></b><div><img src=\"https://clsite-file.s3.amazonaws.com/LSTQuestionImg/773334/887103/93s.gif\">"
        },
        "20003": {
            "id": "20003",
            "marks": 3,
            "negative_marks": 1.0,
            "is_input_type": true,
            "is_multi_select": false,
            "instructions": "",
            "question_text": "\u00a0\u00a0Q.3 [11916616]  Two\n\t\t\t\t\t\t\t\t\tconcentric circles, having their center at O, are cut by a line such that the line\n\t\t\t\t\t\t\t\t\tforms a chord\n\t\t\t\t\t\t\t\t\tfor both the circles. The length of the chord for the smaller circle and the bigger\n\t\t\t\t\t\t\t\t\tcircle is 8m and\n\t\t\t\t\t\t\t\t\t16m respectively. What is the absolute difference between the squares of the radii\n\t\t\t\t\t\t\t\t\t(in cm2) of the\n\t\t\t\t\t\t\t\t\ttwo circles?",
            "options": [],
            "correct_response": [
                [
                    "1"
                ]
            ],
            "solution": "<b><br><b></b><div><img src=\"https://clsite-file.s3.amazonaws.com/LSTQuestionImg/773334/887105/95s.gif\">"
        },
        "20004": {
            "id": "20004",
            "marks": 3,
            "negative_marks": 1.0,
            "is_input_type": false,
            "is_multi_select": false,
            "instructions": "",
            "question_text": "\u00a0\u00a0Q.4 [11916616]  In how many\n\t\t\t\t\t\t\t\tways can four couples be seated around a circular table so that the same gender\n\t\t\t\t\t\t\t\tdoes not get to sit together and exactly one of the four couples sit adjacent to each\n\t\t\t\t\t\t\t\tother?",
            "options": [
                "48",
                "36",
                "24",
                "96"
            ],
            "correct_response": [
                [
                    "1"
                ]
            ],
            "solution": "<b><br><b></b><div><img src=\"https://clsite-file.s3.amazonaws.com/LSTQuestionImg/773334/887090/80s.gif\">"
        },
        "20005": {
            "id": "20005",
            "marks": 3,
            "negative_marks": 1.0,
            "is_input_type": false,
            "is_multi_select": false,
            "instructions": "",
            "question_text": "\u00a0\u00a0Q.5 [11916616]  The average age of\n\t\t\t\t\t\t\ta family of 5 members is 20 years. If the age of the youngest member is 10\n\t\t\t\t\t\t\tyears, what was the approximate average age of the family just a day before the birth of the\n\t\t\t\t\t\t\tyoungest member?",
            "options": [
                "13.5",
                "14",
                "15",
                "12.5"
            ],
            "correct_response": [
                [
                    "1"
                ]
            ],
            "solution": "<b><br><b></b><div><img src=\"https://clsite-file.s3.amazonaws.com/LSTQuestionImg/773334/887088/78s.gif\">"
        },
        "20006": {
            "id": "20006",
            "marks": 3,
            "negative_marks": 1.0,
            "is_input_type": false,
            "is_multi_select": false,
            "instructions": "",
            "question_text": "\u00a0\u00a0Q.6 [11916616]  There are 3 vessels of\n\t\t\t\t\t\tequal volume, filled with mixtures of water and milk in the ratio of 1 : 2, 2 : 3\n\t\t\t\t\t\tand 3 : 4 respectively. They all are poured in a large vessel. What proportion of the liquid\n\t\t\t\t\t\tmust\n\t\t\t\t\t\tbe removed from that vessel and replaced with water of equal quantity so that the resulting\n\t\t\t\t\t\tmixture in the vessel contains 50% milk?",
            "options": [
                "71/244",
                "71/386",
                "71/325",
                "71/193"
            ],
            "correct_response": [
                [
                    "1"
                ]
            ],
            "solution": "<b><br><b></b><div><img src=\"https://clsite-file.s3.amazonaws.com/LSTQuestionImg/773334/887089/79s.gif\">"
        },
        "20007": {
            "id": "20007",
            "marks": 3,
            "negative_marks": 1.0,
            "is_input_type": false,
            "is_multi_select": false,
            "instructions": "",
            "question_text": "\u00a0\u00a0Q.7 [11916616]  Find the sum of the\n\t\t\t\t\tfollowing series upto 10 terms:\n\t\t\t\t\t\n\t\t\t\t",
            "options": [
                "402",
                "505/8",
                "505/2",
                "505/4"
            ],
            "correct_response": [
                [
                    "1"
                ]
            ],
            "solution": "<b><br><b></b><div><img src=\"https://clsite-file.s3.amazonaws.com/LSTQuestionImg/773334/887082/72s.gif\">"
        },
        "20008": {
            "id": "20008",
            "marks": 3,
            "negative_marks": 1.0,
            "is_input_type": false,
            "is_multi_select": false,
            "instructions": "",
            "question_text": "\u00a0\u00a0Q.8 [11916616]  The number of votes not cast\n\t\t\t\tfor the PNC Party increased by 25% in the National General Election\n\t\t\t\t(NGE) as compared to the previous Assembly Polls, and as a result the PNC Party lost in the NGE\n\t\t\t\tby a majority of twice as many votes by which it had won the Assembly Polls. If the total of\n\t\t\t\t2,60,000 people voted each time, then how many of them voted for the PNC Party in the previous\n\t\t\t\tAssembly Polls?",
            "options": [
                "1,10,000",
                "1,50,000",
                "1,40,000",
                "1,20,000"
            ],
            "correct_response": [
                [
                    "1"
                ]
            ],
            "solution": "<b><br><b></b><div><img src=\"https://clsite-file.s3.amazonaws.com/LSTQuestionImg/773334/887083/73s.gif\">"
        },
        "20009": {
            "id": "20009",
            "marks": 3,
            "negative_marks": 1.0,
            "is_input_type": true,
            "is_multi_select": false,
            "instructions": "",
            "question_text": "\u00a0\u00a0Q.9 [11916616]  Find the number of common\n\t\t\t\troots of the following cubic equations:\n\t\t\t\t7x3 + 9x2 + 11x + 13 = 0 and 7x3 + 8x2 + 16x + 7 = 0",
            "options": [],
            "correct_response": [
                [
                    "1"
                ]
            ],
            "solution": "<b><br><b></b><div><img src=\"https://clsite-file.s3.amazonaws.com/LSTQuestionImg/773334/887109/99s.gif\">"
        },
        "20010": {
            "id": "20010",
            "marks": 3,
            "negative_marks": 1.0,
            "is_input_type": false,
            "is_multi_select": false,
            "instructions": "",
            "question_text": "\u00a0\u00a0Q.10 [11916616]  If f(x + y, x \u2013 y) = x \u00d7 y,\n\t\t\t\tthen find the expression for f(x, y).",
            "options": [
                "None of these"
            ],
            "correct_response": [
                [
                    "1"
                ]
            ],
            "solution": "<b><br><b></b><div><img src=\"https://clsite-file.s3.amazonaws.com/LSTQuestionImg/773334/887081/71s.gif\">"
        },
        "20011": {
            "id": "20011",
            "marks": 3,
            "negative_marks": 1.0,
            "is_input_type": true,
            "is_multi_select": false,
            "instructions": "",
            "question_text": "\u00a0\u00a0Q.11 [11916616]  The monthly telephone bills\n\t\t\t\tof a company has a fixed tariff of Rs. 250 for up to 50 outgoing calls, above\n\t\t\t\twhich charge of Rs. 1.25 per call needs to be paid. If the ratio of the monthly bills paid by A and B\n\t\t\t\tis 2 : 3 and the number of outgoing calls by A is 90, then what is the total number of outgoing calls\n\t\t\t\tmade by B in that month?",
            "options": [],
            "correct_response": [
                [
                    "1"
                ]
            ],
            "solution": "<b><br><b></b><div><img src=\"https://clsite-file.s3.amazonaws.com/LSTQuestionImg/773334/887092/82s.gif\">"
        },
        "20012": {
            "id": "20012",
            "marks": 3,
            "negative_marks": 1.0,
            "is_input_type": true,
            "is_multi_select": false,
            "instructions": "",
            "question_text": "\u00a0\u00a0Q.12 [11916616]  How many 3-digit numbers\n\t\t\t\tleave a remainder of 4 when divided by 21 and a remainder of 8 when\n\t\t\t\tdivided by 13?",
            "options": [],
            "correct_response": [
                [
                    "1"
                ]
            ],
            "solution": "<b><br><b></b><div><img src=\"https://clsite-file.s3.amazonaws.com/LSTQuestionImg/773334/887093/83s.gif\">"
        },
        "20013": {
            "id": "20013",
            "marks": 3,
            "negative_marks": 1.0,
            "is_input_type": false,
            "is_multi_select": false,
            "instructions": "",
            "question_text": "\u00a0\u00a0Q.13 [11916616]  Two cars A and B start\n\t\t\t\tsimultaneously from two points P and Q respectively, located at a distance\n\t\t\t\tof 200 metres and 800 metres respectively from the point of intersection of two perpendicular roads\n\t\t\t\tL1 and L2. Car A is moving along the road L1 and is going away from the\n\t\t\t\tpoint of intersection of the\n\t\t\t\ttwo roads while car B is moving along the road L2 and is moving towards the point of\n\t\t\t\tintersection of the\n\t\t\t\troads. If after 2 minutes and again after 6 minutes from the start, the two cars are at equal distance\n\t\t\t\tfrom the\n\t\t\t\tpoint of intersection of the roads, then find the ratio of the speeds of the two cars.",
            "options": [
                "1 : 1",
                "1 : 4",
                "2 : 7",
                "2 : 5"
            ],
            "correct_response": [
                [
                    "1"
                ]
            ],
            "solution": "<b><br><b></b><div><img src=\"https://clsite-file.s3.amazonaws.com/LSTQuestionImg/773334/887097/87s.gif\">"
        },
        "20014": {
            "id": "20014",
            "marks": 3,
            "negative_marks": 1.0,
            "is_input_type": false,
            "is_multi_select": false,
            "instructions": "",
            "question_text": "\u00a0\u00a0Q.14 [11916616]  ",
            "options": [
                "1",
                "\u20131",
                "2",
                "Both (1) and (2)"
            ],
            "correct_response": [
                [
                    "1"
                ]
            ],
            "solution": "<b><br><b></b><div><img src=\"https://clsite-file.s3.amazonaws.com/LSTQuestionImg/773334/887099/89s.gif\">"
        },
        "20015": {
            "id": "20015",
            "marks": 3,
            "negative_marks": 1.0,
            "is_input_type": false,
            "is_multi_select": false,
            "instructions": "",
            "question_text": "\u00a0\u00a0Q.15 [11916616]  If |x + 1| + |x| + |x \u2013 1| +\n\t\t\t\t|x \u2013 1| + |x \u2013 2| + |x \u2013 3| \u2264 30, then for how many integral values of x does this hold true?",
            "options": [
                "9",
                "11",
                "12",
                "15"
            ],
            "correct_response": [
                [
                    "1"
                ]
            ],
            "solution": "<b><br><b></b><div><img src=\"https://clsite-file.s3.amazonaws.com/LSTQuestionImg/773334/887091/81s.gif\">"
        },
        "20016": {
            "id": "20016",
            "marks": 3,
            "negative_marks": 1.0,
            "is_input_type": false,
            "is_multi_select": false,
            "instructions": "",
            "question_text": "\u00a0\u00a0Q.16 [11916616]  A trader buys goods at a 19%\n\t\t\t\tdiscount on the label price. If he wants to make a profit of 20% after\n\t\t\t\tallowing a discount of 10%, then by what percentage should his marked price be greater than the original\n\t\t\t\tlabel\n\t\t\t\tprice?",
            "options": [
                "8%",
                "3.8%",
                "33.33%",
                "None of these"
            ],
            "correct_response": [
                [
                    "1"
                ]
            ],
            "solution": "<b><br><b></b><div><img src=\"https://clsite-file.s3.amazonaws.com/LSTQuestionImg/773333/885265/82s.gif\">"
        },
        "20017": {
            "id": "20017",
            "marks": 3,
            "negative_marks": 1.0,
            "is_input_type": false,
            "is_multi_select": false,
            "instructions": "",
            "question_text": "\u00a0\u00a0Q.17 [11916616]  If P = x2 +\n\t\t\t\t5y2 \u2013 4xy + 6y + 29 where x and y are integers such that \u20138 \u2264 y \u2264 1 and \u20133 \u2264 x \u2264 2, then\n\t\t\t\twhich of the\n\t\t\t\tfollowing is always true?\n\t\t\t",
            "options": [
                "P can never be more than 270",
                "P can never be more than 301",
                "P can never be less than 29",
                "P can never be less than 22"
            ],
            "correct_response": [
                [
                    "1"
                ]
            ],
            "solution": "<b><br><b></b><div><br>"
        },
        "20018": {
            "id": "20018",
            "marks": 3,
            "negative_marks": 1.0,
            "is_input_type": false,
            "is_multi_select": false,
            "instructions": "",
            "question_text": "\u00a0\u00a0Q.18 [11916616]  A sum of money becomes 8\n\t\t\t\ttimes in 27 years at r% compound interest. Had the same amount was\n\t\t\t\tinvested at r% simple interest for 27 years, then how many times would the amount have become after 27\n\t\t\t\tyears?",
            "options": [
                "greater than 4 times",
                "greater than 3 times but less than 4 times",
                "greater than 2 times but less than 3 times",
                "greater than 6 times"
            ],
            "correct_response": [
                [
                    "1"
                ]
            ],
            "solution": "<b><br><b></b><div><img src=\"https://clsite-file.s3.amazonaws.com/LSTQuestionImg/773334/887100/90s.gif\">"
        },
        "20019": {
            "id": "20019",
            "marks": 3,
            "negative_marks": 1.0,
            "is_input_type": true,
            "is_multi_select": false,
            "instructions": "",
            "question_text": "\u00a0\u00a0Q.19 [11916616]  How many integral values of\n\t\t\t\t(x, y) satisfy the equation x2 \u2013 y2 = 220?",
            "options": [],
            "correct_response": [
                [
                    "1"
                ]
            ],
            "solution": "<b><br><b></b><div><br><br><br><br><br><br><br><br><br><br><br><br><br><br><br><br><br>"
        },
        "20020": {
            "id": "20020",
            "marks": 3,
            "negative_marks": 1.0,
            "is_input_type": false,
            "is_multi_select": false,
            "instructions": "",
            "question_text": "\u00a0\u00a0Q.20 [11916616]  If A = {91, 92, 93, \u2026, 180}\n\t\t\t\tand B is a subset of A such that the sum of no two elements of B is a multiple of 9, then what can be\n\t\t\t\tthe maximum number of elements\n\t\t\t\tin B?",
            "options": [
                "24",
                "50",
                "41",
                "45"
            ],
            "correct_response": [
                [
                    "1"
                ]
            ],
            "solution": "<b><br><b></b><div><img src=\"https://clsite-file.s3.amazonaws.com/LSTQuestionImg/773334/887098/88s.gif\">"
        },
        "20021": {
            "id": "20021",
            "marks": 3,
            "negative_marks": 1.0,
            "is_input_type": true,
            "is_multi_select": false,
            "instructions": "",
            "question_text": "\u00a0\u00a0Q.21 [11916616]  In the figure given below, a\n\t\t\t\tcircle with the centre at O and a rectangle ABCD are drawn. The circle\n\t\t\t\ttouches side CD at E and passes through the points A and F. If AO = 3 cm, DF = 1 cm and DC =\n\t\t\t\t8 cm, then the area (in cm2) of rectangle ABCD is",
            "options": [],
            "correct_response": [
                [
                    "1"
                ]
            ],
            "solution": "<b><br><b></b><div>"
        },
        "20022": {
            "id": "20022",
            "marks": 3,
            "negative_marks": 1.0,
            "is_input_type": true,
            "is_multi_select": false,
            "instructions": "",
            "question_text": "\u00a0\u00a0Q.22 [11916616]  A and B start running\n\t\t\t\tsimultaneously towards each other from the two ends of a track XY and the ratio of their speeds is 3 :\n\t\t\t\t4. Every time they meet, they interchange their speeds and also reverse\n\t\t\t\ttheir directions. At how many distinct points on the track do they meet each other, if they run\n\t\t\t\tcontinuously between 2 ends of the tracks? (Track XY is shown below)",
            "options": [],
            "correct_response": [
                [
                    "1"
                ]
            ],
            "solution": "<p>Explanation not available.</p>"
        }
    }
}